http_api/__init__.py
http_api/example.py
http_api/http_api.py
http_api/map.py
http_api/security.py
http_api/server.py
http_api/utils.py
http_api-0.2.2.dist-info/LICENSE
http_api-0.2.2.dist-info/METADATA
http_api-0.2.2.dist-info/WHEEL
http_api-0.2.2.dist-info/top_level.txt
http_api-0.2.2.dist-info/RECORD
