Metadata-Version: 2.1
Name: http-api
Version: 0.2.2
Summary: HTTP API for Python using builtin SimpleHTTPServer
Home-page: UNKNOWN
Author: Syban
Author-email: author@example.com
License: UNKNOWN
Platform: UNKNOWN
Classifier: Programming Language :: Python :: 3
Classifier: Operating System :: OS Independent
Classifier: Topic :: Internet :: WWW/HTTP :: HTTP Servers
Requires-Python: >=3.0
